{"0100BRA10599":{"atcoCode":"0100BRA10599","naptanCode":"bstagap","category":"bus","stopType":"BCT","onStreet":true,"name":"Priory Gardens","landmark":"","street":"","crossing":"","locality":"Shirehampton","town":"","suburb":"","coordinates":[-2.67956,51.491],"indicator":"N-bound","properties":{"type":"marked","stopSubType":"MKD","bearing":"N","section":[],"timingStatus":"OTH","annotatedCoachRef":{}},"stopArea":[],"adminArea":"009","plusbusZone":[],"created":"2007-05-21T00:00:00","updated":"2016-10-31T11:01:15","status":"active","validity":[]}}