{"021024031":{"atcoCode":"021024031","naptanCode":"ahlagwtg","category":"bus","stopType":"BCT","onStreet":true,"name":"Franklin Close","landmark":"","street":"","crossing":"","locality":"Lower Shelton","town":"","suburb":"","coordinates":[-0.54548,52.07281],"indicator":"adj","properties":{"type":"marked","stopSubType":"MKD","bearing":"SE","section":[],"timingStatus":"OTH","annotatedCoachRef":{}},"stopArea":[],"adminArea":"151","plusbusZone":[],"created":"2020-09-09T00:00:00","updated":"2024-06-18T14:13:01","status":"active","validity":[]}}