{"039025470001":{"atcoCode":"039025470001","naptanCode":"rdgajdj","category":"bus","stopType":"BCT","onStreet":true,"name":"Caversham Road Fire Station","landmark":"","street":"","crossing":"","locality":"Reading","town":"","suburb":"","coordinates":[-0.97588,51.46023],"indicator":"opp","properties":{"type":"marked","stopSubType":"MKD","bearing":"SW","section":[],"timingStatus":"OTH","annotatedCoachRef":{}},"stopArea":["039G25470001"],"adminArea":"046","plusbusZone":[],"created":"2006-02-01T00:00:00","updated":"2022-04-04T16:27:01","status":"active","validity":[]}}