{"040000002608":{"atcoCode":"040000002608","naptanCode":"bucdgwjm","category":"bus","stopType":"BCT","onStreet":true,"name":"Blackhorse Bridge","landmark":"","street":"","crossing":"","locality":"Amersham","town":"","suburb":"","coordinates":[-0.591259,51.672548],"indicator":"Opp","properties":{"type":"marked","stopSubType":"MKD","bearing":"W","section":[],"timingStatus":"TIP","annotatedCoachRef":{}},"stopArea":["040G00002607"],"adminArea":"070","plusbusZone":[],"created":"2006-06-12T00:00:00.000","updated":"2008-04-11T00:00:00.000","status":"active","validity":[]}}