{"0590PC452":{"atcoCode":"0590PC452","naptanCode":"PETMWGM","category":"bus","stopType":"BCT","onStreet":true,"name":"St John's Post Office","landmark":"","street":"","crossing":"","locality":"Peterborough","town":"","suburb":"","coordinates":[-0.23650328758336123,52.57368792211214],"indicator":"opp","properties":{"type":"marked","stopSubType":"MKD","bearing":"N","section":[],"timingStatus":"OTH","annotatedCoachRef":{}},"stopArea":["059GPB64"],"adminArea":"041","plusbusZone":[],"created":"2006-05-02T00:00:00","updated":"2008-11-07T00:00:00","status":"inactive","validity":[{"validityStart":"2008-11-07","validityEnd":"","status":"","transferToStop":"","remarks":"Stop removed"}]}}