{"0610CH2478":{"atcoCode":"0610CH2478","naptanCode":"CHWDJPW","category":"bus","stopType":"BCT","onStreet":true,"name":"Maternity Wing","landmark":"","street":"","crossing":"","locality":"Bache","town":"","suburb":"","coordinates":[-2.8968782,53.2086657],"indicator":"o/s","properties":{"type":"marked","stopSubType":"MKD","bearing":"SW","section":[],"timingStatus":"PTP","annotatedCoachRef":{}},"stopArea":["061GCH26"],"adminArea":"152","plusbusZone":["CHST"],"created":"2006-04-19T00:00:00.000","updated":"2020-07-14T10:24:52.000","status":"active","validity":[]}}