{"0610CHIM173":{"atcoCode":"0610CHIM173","naptanCode":"CHWTMPA","category":"bus","stopType":"BCT","onStreet":true,"name":"Ashley Court Mews","landmark":"","street":"","crossing":"","locality":"Cuddington Green","town":"","suburb":"","coordinates":[-2.8064651,53.0136252],"indicator":"o/s","properties":{"type":"custom","stopSubType":"CUS","bearing":"SW","section":[],"timingStatus":"OTH","annotatedCoachRef":{}},"stopArea":[],"adminArea":"152","plusbusZone":[],"created":"2003-01-14T00:00:00.000","updated":"2012-02-21T12:45:25.000","status":"inactive","validity":[]}}