{"078074719B":{"atcoCode":"078074719B","naptanCode":"recdtpm","category":"bus","stopType":"BCT","onStreet":true,"name":"Oakley Close","landmark":"","street":"","crossing":"","locality":"Guisborough","town":"","suburb":"","coordinates":[-1.047466,54.526092],"indicator":"B","properties":{"type":"marked","stopSubType":"MKD","bearing":"S","section":[],"timingStatus":"OTH","annotatedCoachRef":{}},"stopArea":["078G74719"],"adminArea":"047","plusbusZone":[],"created":"2006-09-26T00:00:00.000","updated":"2017-10-12T17:30:59.187","status":"active","validity":[]}}