{"0800FWX38714":{"atcoCode":"0800FWX38714","naptanCode":"coratdmj","category":"bus","stopType":"BCT","onStreet":true,"name":"Truro Hill","landmark":"","street":"","crossing":"","locality":"Penryn","town":"","suburb":"","coordinates":[-5.1059,50.17212],"indicator":"NW-bound","properties":{"type":"marked","stopSubType":"MKD","bearing":"NW","section":[],"timingStatus":"OTH","annotatedCoachRef":{}},"stopArea":[],"adminArea":"073","plusbusZone":[],"created":"2003-06-12T00:00:00","updated":"2025-08-05T10:29:37","status":"active","validity":[]}}