{"1100DEC10740":{"atcoCode":"1100DEC10740","naptanCode":"dvngadpd","category":"bus","stopType":"BCT","onStreet":true,"name":"Brook","landmark":"","street":"","crossing":"","locality":"East Budleigh","town":"","suburb":"","coordinates":[-3.31804,50.65154],"indicator":"opp","properties":{"type":"marked","stopSubType":"MKD","bearing":"W","section":[],"timingStatus":"OTH","annotatedCoachRef":{}},"stopArea":[],"adminArea":"076","plusbusZone":[],"created":"2003-06-12T00:00:00","updated":"2024-12-04T14:10:11","status":"active","validity":[]}}