{"1100DEB11419":{"atcoCode":"1100DEB11419","naptanCode":"dvngapam","category":"bus","stopType":"BCT","onStreet":true,"name":"Winslade Road","landmark":"","street":"","crossing":"","locality":"Sidmouth","town":"","suburb":"","coordinates":[-3.23877,50.69048],"indicator":"SE-bound","properties":{"type":"marked","stopSubType":"MKD","bearing":"SE","section":[],"timingStatus":"OTH","annotatedCoachRef":{}},"stopArea":[],"adminArea":"076","plusbusZone":[],"created":"2003-06-12T00:00:00","updated":"2020-08-11T10:43:35","status":"active","validity":[]}}