{"1100DEC11486":{"atcoCode":"1100DEC11486","naptanCode":"dvndtmgj","category":"bus","stopType":"BCT","onStreet":true,"name":"Post Hill","landmark":"","street":"","crossing":"","locality":"Tiverton, Devon","town":"","suburb":"","coordinates":[-3.44132,50.90997],"indicator":"E-bound","properties":{"type":"custom","stopSubType":"CUS","bearing":"E","section":[],"timingStatus":"OTH","annotatedCoachRef":{}},"stopArea":[],"adminArea":"076","plusbusZone":[],"created":"2003-06-12T00:00:00","updated":"2018-11-15T15:44:10","status":"inactive","validity":[]}}