{"1280POA11593":{"atcoCode":"1280POA11593","naptanCode":"plegmdt","category":"bus","stopType":"BCT","onStreet":true,"name":"Uppleby Road","landmark":"","street":"","crossing":"","locality":"Parkstone","town":"","suburb":"","coordinates":[-1.9436,50.72915],"indicator":"E-bound","properties":{"type":"marked","stopSubType":"MKD","bearing":"E","section":[],"timingStatus":"OTH","annotatedCoachRef":{}},"stopArea":[],"adminArea":"043","plusbusZone":[],"created":"2005-11-09T00:00:00","updated":"2021-07-07T13:30:46","status":"active","validity":[]}}