{"13004234G":{"atcoCode":"13004234G","naptanCode":"durawjwa","category":"bus","stopType":"BCT","onStreet":true,"name":"Croftside","landmark":"","street":"","crossing":"","locality":"Etherley Dene","town":"Etherley Dene","suburb":"","coordinates":[-1.707024,54.655354],"indicator":"W-bound","properties":{"type":"marked","stopSubType":"MKD","bearing":"W","section":[],"timingStatus":"OTH","annotatedCoachRef":{}},"stopArea":[],"adminArea":"078","plusbusZone":[],"created":"2005-06-02T00:00:00.000","updated":"2025-10-27T07:16:06.484","status":"active","validity":[]}}