{"13007836B":{"atcoCode":"13007836B","naptanCode":"","category":"bus","stopType":"BCT","onStreet":true,"name":"Bus stop","landmark":"","street":"","crossing":"","locality":"Middleton in Teesdale","town":"Nettle Pot","suburb":"","coordinates":[-2.125143,54.595011],"indicator":"north east bound","properties":{"type":"marked","stopSubType":"MKD","bearing":"NE","section":[],"timingStatus":"OTH","annotatedCoachRef":{}},"stopArea":[],"adminArea":"078","plusbusZone":[],"created":"2005-06-02T00:00:00.000","updated":"2005-06-02T00:00:00.000","status":"inactive","validity":[]}}