{"1490105680":{"atcoCode":"1490105680","naptanCode":"brimtgj","category":"bus","stopType":"BCT","onStreet":true,"name":"Easthill Way","landmark":"","street":"","crossing":"","locality":"Portslade","town":"","suburb":"","coordinates":[-0.215511,50.843348],"indicator":"adj","properties":{"type":"custom","stopSubType":"CUS","bearing":"S","section":[],"timingStatus":"OTH","annotatedCoachRef":{}},"stopArea":[],"adminArea":"008","plusbusZone":["BRGHTN"],"created":"2013-02-12T16:19:00.000","updated":"2017-01-30T14:41:00.000","status":"inactive","validity":[]}}