{"1500IM633":{"atcoCode":"1500IM633","naptanCode":"esxajgdg","category":"bus","stopType":"BCT","onStreet":true,"name":"War Memorial","landmark":"","street":"","crossing":"","locality":"Stock, Essex","town":"Stock","suburb":"","coordinates":[0.4445046024,51.6642554064],"indicator":"opp","properties":{"type":"marked","stopSubType":"MKD","bearing":"SW","section":[],"timingStatus":"OTH","annotatedCoachRef":{}},"stopArea":["150G00000441"],"adminArea":"080","plusbusZone":[],"created":"2006-11-06T00:00:00","updated":"2023-08-17T08:48:27","status":"active","validity":[]}}