{"1600GLS677":{"atcoCode":"1600GLS677","naptanCode":"glodatmt","category":"bus","stopType":"BCT","onStreet":true,"name":"Spillman's Pitch","landmark":"","street":"","crossing":"","locality":"Rodborough","town":"","suburb":"","coordinates":[-2.22845,51.74117],"indicator":"before","properties":{"type":"marked","stopSubType":"MKD","bearing":"SW","section":[],"timingStatus":"OTH","annotatedCoachRef":{}},"stopArea":[],"adminArea":"081","plusbusZone":[],"created":"2017-12-13T00:00:00","updated":"2017-12-13T13:13:47","status":"active","validity":[]}}