{"160000596":{"atcoCode":"160000596","naptanCode":"glojagag","category":"bus","stopType":"BCT","onStreet":true,"name":"Greenacres","landmark":"","street":"","crossing":"","locality":"Bishops Cleeve","town":"","suburb":"","coordinates":[-2.06875,51.95104],"indicator":"nr","properties":{"type":"marked","stopSubType":"MKD","bearing":"SW","section":[],"timingStatus":"OTH","annotatedCoachRef":{}},"stopArea":[],"adminArea":"081","plusbusZone":[],"created":"2017-08-17T00:00:00","updated":"2024-11-04T15:39:03","status":"active","validity":[]}}