{"1800EB31701":{"atcoCode":"1800EB31701","naptanCode":"MANAGPJM","category":"bus","stopType":"BCT","onStreet":true,"name":"Droylsden Road","landmark":"","street":"","crossing":"","locality":"Newton Heath","town":"","suburb":"","coordinates":[-2.179113,53.50335],"indicator":"opp","properties":{"type":"marked","stopSubType":"MKD","bearing":"E","section":[],"timingStatus":"OTH","annotatedCoachRef":{}},"stopArea":[],"adminArea":"083","plusbusZone":["MNCRPIC"],"created":"2007-11-05T00:00:00.000","updated":"2023-07-21T09:13:06.000","status":"active","validity":[]}}