{"1800NC21671":{"atcoCode":"1800NC21671","naptanCode":"MANDPTAM","category":"bus","stopType":"BCT","onStreet":true,"name":"Chesham Fold Road","landmark":"","street":"","crossing":"","locality":"Fern Grove","town":"","suburb":"","coordinates":[-2.275047,53.60146],"indicator":"nr","properties":{"type":"marked","stopSubType":"MKD","bearing":"W","section":[],"timingStatus":"OTH","annotatedCoachRef":{}},"stopArea":[],"adminArea":"083","plusbusZone":[],"created":"2010-04-23T00:00:00.000","updated":"2023-07-21T09:13:08.000","status":"active","validity":[]}}