{"1800WK46251":{"atcoCode":"1800WK46251","naptanCode":"MANTDTGD","category":"bus","stopType":"BCT","onStreet":true,"name":"The Alexandra","landmark":"","street":"","crossing":"","locality":"New Springs","town":"","suburb":"","coordinates":[-2.612848,53.55563],"indicator":"The Alexandra","properties":{"type":"marked","stopSubType":"MKD","bearing":"SW","section":[],"timingStatus":"OTH","annotatedCoachRef":{}},"stopArea":[],"adminArea":"083","plusbusZone":["MNCRPIC"],"created":"2007-11-01T00:00:00.000","updated":"2023-07-21T09:13:25.000","status":"inactive","validity":[]}}