{"1900HA010194":{"atcoCode":"1900HA010194","naptanCode":"hamdwdwd","category":"bus","stopType":"BCT","onStreet":true,"name":"Roman Way","landmark":"","street":"","crossing":"","locality":"Worting","town":"","suburb":"","coordinates":[-1.13811,51.26187],"indicator":"E-bound","properties":{"type":"marked","stopSubType":"MKD","bearing":"E","section":[],"timingStatus":"OTH","annotatedCoachRef":{}},"stopArea":[],"adminArea":"084","plusbusZone":[],"created":"2005-10-07T00:00:00","updated":"2021-05-25T06:11:56","status":"active","validity":[]}}