{"1900HA110820":{"atcoCode":"1900HA110820","naptanCode":"hamdgmtg","category":"bus","stopType":"BCT","onStreet":true,"name":"Peter Symonds","landmark":"","street":"","crossing":"","locality":"Fulflood","town":"","suburb":"","coordinates":[-1.32188,51.07211],"indicator":"outside","properties":{"type":"marked","stopSubType":"MKD","bearing":"SW","section":[],"timingStatus":"OTH","annotatedCoachRef":{}},"stopArea":[],"adminArea":"084","plusbusZone":[],"created":"2007-02-25T00:00:00","updated":"2018-04-16T14:26:29","status":"active","validity":[]}}