{"210021604950":{"atcoCode":"210021604950","naptanCode":"hrtapdtp","category":"bus","stopType":"BCT","onStreet":true,"name":"The District Cemetery","landmark":"","street":"","crossing":"","locality":"South Hatfield","town":"Hatfield","suburb":"","coordinates":[-0.231486570416306,51.74234827905519],"indicator":"nr","properties":{"type":"marked","stopSubType":"MKD","bearing":"SW","section":[],"timingStatus":"OTH","annotatedCoachRef":{}},"stopArea":["210G938"],"adminArea":"085","plusbusZone":[],"created":"2004-06-17T11:22:08","updated":"2010-05-27T12:12:24","status":"active","validity":[{"validityStart":"2005-05-17","validityEnd":"","status":"","transferToStop":"","remarks":""}]}}