{"210021301990":{"atcoCode":"210021301990","naptanCode":"hrtjdpmp","category":"bus","stopType":"BCT","onStreet":true,"name":"Phillips Way","landmark":"","street":"","crossing":"","locality":"Buntingford","town":"Buntingford","suburb":"","coordinates":[-0.0291787789359,51.95665033194269],"indicator":"nr","properties":{"type":"marked","stopSubType":"MKD","bearing":"SE","section":[],"timingStatus":"OTH","annotatedCoachRef":{}},"stopArea":[],"adminArea":"085","plusbusZone":[],"created":"2020-03-10T09:25:36","updated":"2025-06-04T08:00:33","status":"active","validity":[{"validityStart":"2025-04-30","validityEnd":"","status":"","transferToStop":"","remarks":""}]}}