{"210021309515":{"atcoCode":"210021309515","naptanCode":"hrtdpjma","category":"bus","stopType":"BCT","onStreet":true,"name":"Watersplace Farm","landmark":"","street":"","crossing":"","locality":"Easneye","town":"Ware","suburb":"","coordinates":[0.005387589967709,51.811382415228344],"indicator":"adj","properties":{"type":"custom","stopSubType":"CUS","bearing":"SW","section":[],"timingStatus":"OTH","annotatedCoachRef":{}},"stopArea":["210G339"],"adminArea":"085","plusbusZone":[],"created":"2004-06-17T11:22:08","updated":"2008-01-23T15:18:40","status":"active","validity":[{"validityStart":"2005-03-10","validityEnd":"","status":"","transferToStop":"","remarks":""}]}}