{"210021108000":{"atcoCode":"210021108000","naptanCode":"hrtgjdgj","category":"bus","stopType":"BCT","onStreet":true,"name":"Post Office","landmark":"","street":"","crossing":"","locality":"Great Offley","town":"Great Offley","suburb":"","coordinates":[-0.341618781990747,51.929851121178835],"indicator":"opp","properties":{"type":"marked","stopSubType":"MKD","bearing":"SW","section":[],"timingStatus":"TIP","annotatedCoachRef":{}},"stopArea":["210G1898"],"adminArea":"085","plusbusZone":[],"created":"2004-06-17T11:22:08","updated":"2009-05-29T10:03:20","status":"active","validity":[{"validityStart":"2004-11-26","validityEnd":"","status":"","transferToStop":"","remarks":""}]}}