{"230000004190":{"atcoCode":"230000004190","naptanCode":"iowdjdg","category":"bus","stopType":"BCT","onStreet":true,"name":"Boots","landmark":"","street":"","crossing":"","locality":"Ventnor","town":"","suburb":"","coordinates":[-1.2058,50.5952],"indicator":"adjacent","properties":{"type":"marked","stopSubType":"MKD","bearing":"NE","section":[],"timingStatus":"OTH","annotatedCoachRef":{}},"stopArea":[],"adminArea":"025","plusbusZone":[],"created":"2006-06-02T00:00:00","updated":"2016-04-21T09:46:24","status":"active","validity":[]}}