{"2490103130":{"atcoCode":"2490103130","naptanCode":"chajwdp","category":"bus","stopType":"BCT","onStreet":true,"name":"Strood Academy","landmark":"","street":"","crossing":"","locality":"Strood, Medway","town":"","suburb":"","coordinates":[0.4650433,51.3985435],"indicator":"o/s","properties":{"type":"custom","stopSubType":"CUS","bearing":"W","section":[],"timingStatus":"PTP","annotatedCoachRef":{}},"stopArea":[],"adminArea":"029","plusbusZone":["CHATHAM"],"created":"2010-07-16T12:12:00.000","updated":"2019-05-28T11:45:00.000","status":"active","validity":[]}}