{"260024000":{"atcoCode":"260024000","naptanCode":"leijpamd","category":"bus","stopType":"BCT","onStreet":true,"name":"Buccaneer Way","landmark":"","street":"","crossing":"","locality":"Magna Park, Leics","town":"","suburb":"","coordinates":[-1.241921,52.458177],"indicator":"adj","properties":{"type":"marked","stopSubType":"MKD","bearing":"N","section":[],"timingStatus":"OTH","annotatedCoachRef":{}},"stopArea":[],"adminArea":"088","plusbusZone":[],"created":"2002-12-10T00:00:00.000","updated":"2019-07-30T11:53:01.041","status":"active","validity":[]}}