{"2700LWB04852":{"atcoCode":"2700LWB04852","naptanCode":"linawjwd","category":"bus","stopType":"BCT","onStreet":true,"name":"Cliff Road","landmark":"","street":"","crossing":"","locality":"Woolsthorpe by Belvoir","town":"","suburb":"","coordinates":[-0.756734236,52.899254749],"indicator":"NE-bound","properties":{"type":"marked","stopSubType":"MKD","bearing":"NE","section":[],"timingStatus":"TIP","annotatedCoachRef":{}},"stopArea":[],"adminArea":"089","plusbusZone":[],"created":"2004-11-09T00:00:00","updated":"2020-06-11T10:07:02","status":"active","validity":[]}}