{"2900D121":{"atcoCode":"2900D121","naptanCode":"NFOAMJPW","category":"bus","stopType":"BCT","onStreet":true,"name":"Village Sign","landmark":"","street":"","crossing":"","locality":"Great Dunham","town":"","suburb":"","coordinates":[0.7689726288024744,52.69593299055944],"indicator":"opp","properties":{"type":"marked","stopSubType":"MKD","bearing":"NE","section":[],"timingStatus":"OTH","annotatedCoachRef":{}},"stopArea":["290G1363"],"adminArea":"091","plusbusZone":[],"created":"2003-02-22T14:04:04","updated":"2019-10-30T10:59:31","status":"active","validity":[]}}