{"2900S703":{"atcoCode":"2900S703","naptanCode":"NFOGPGJA","category":"bus","stopType":"BCT","onStreet":true,"name":"Fishmongers Tavern","landmark":"","street":"","crossing":"","locality":"Sheringham","town":"","suburb":"","coordinates":[1.216995176353948,52.93969804120078],"indicator":"adj","properties":{"type":"marked","stopSubType":"MKD","bearing":"E","section":[],"timingStatus":"OTH","annotatedCoachRef":{}},"stopArea":[],"adminArea":"091","plusbusZone":[],"created":"2008-01-14T15:54:04","updated":"2024-04-24T15:20:16","status":"active","validity":[]}}