{"300000473CO":{"atcoCode":"300000473CO","naptanCode":"nthdadap","category":"bus","stopType":"BCT","onStreet":true,"name":"Northampton College","landmark":"","street":"","crossing":"","locality":"Boothville","town":"Northampton","suburb":"Boothville","coordinates":[-0.84847902,52.262642977],"indicator":"opp","properties":{"type":"marked","stopSubType":"MKD","bearing":"SW","section":[],"timingStatus":"TIP","annotatedCoachRef":{}},"stopArea":["300G007"],"adminArea":"093","plusbusZone":["NMPTN"],"created":"2004-11-17T00:00:00","updated":"2010-07-09T12:14:53","status":"active","validity":[]}}