{"3200YNA90186":{"atcoCode":"3200YNA90186","naptanCode":"32090186","category":"bus","stopType":"BCT","onStreet":true,"name":"Rawlinson Road","landmark":"","street":"","crossing":"","locality":"Hipswell","town":"Richmondshire","suburb":"Hipswell","coordinates":[-1.726942,54.383971],"indicator":"N-bound","properties":{"type":"custom","stopSubType":"CUS","bearing":"N","section":[],"timingStatus":"OTH","annotatedCoachRef":{}},"stopArea":[],"adminArea":"092","plusbusZone":[],"created":"2005-05-09T12:00:00.000","updated":"2011-05-18T12:00:00.000","status":"active","validity":[]}}