{"3200YNA00412":{"atcoCode":"3200YNA00412","naptanCode":"32000412","category":"bus","stopType":"BCT","onStreet":true,"name":"Waterside","landmark":"","street":"","crossing":"","locality":"Fairburn","town":"Selby","suburb":"Fairburn","coordinates":[-1.282218,53.741372],"indicator":"opp","properties":{"type":"custom","stopSubType":"CUS","bearing":"NW","section":[],"timingStatus":"OTH","annotatedCoachRef":{}},"stopArea":[],"adminArea":"092","plusbusZone":[],"created":"2003-11-17T12:00:00.000","updated":"2011-05-18T12:00:00.000","status":"inactive","validity":[]}}