{"3200YNE04336":{"atcoCode":"3200YNE04336","naptanCode":"32004336","category":"bus","stopType":"BCT","onStreet":true,"name":"Sleights Lane","landmark":"","street":"","crossing":"","locality":"Staupes","town":"Harrogate","suburb":"Staupes","coordinates":[-1.670879,54.019275],"indicator":"SW-bound","properties":{"type":"custom","stopSubType":"CUS","bearing":"SW","section":[],"timingStatus":"OTH","annotatedCoachRef":{}},"stopArea":[],"adminArea":"092","plusbusZone":[],"created":"2003-11-17T12:00:00.000","updated":"2011-05-18T12:00:00.000","status":"active","validity":[]}}