{"3390WO71":{"atcoCode":"3390WO71","naptanCode":"ntmapmpm","category":"bus","stopType":"BCT","onStreet":true,"name":"Grangewood Road","landmark":"","street":"","crossing":"","locality":"Wollaton","town":"Nottingham","suburb":"Wollaton","coordinates":[-1.2414895,52.947758],"indicator":"Stop WO71","properties":{"type":"marked","stopSubType":"MKD","bearing":"NE","section":[],"timingStatus":"OTH","annotatedCoachRef":{}},"stopArea":["339GWO71"],"adminArea":"039","plusbusZone":["NTNG"],"created":"2003-07-21T00:00:00.000","updated":"2016-11-02T14:05:08.726","status":"active","validity":[]}}