{"340000693EAS":{"atcoCode":"340000693EAS","naptanCode":"oxfgmtdm","category":"bus","stopType":"BCT","onStreet":true,"name":"The Plough","landmark":"","street":"","crossing":"","locality":"Lower Arncott","town":"Lower Arncott","suburb":"","coordinates":[-1.11271,51.85667],"indicator":"E-bound","properties":{"type":"custom","stopSubType":"CUS","bearing":"E","section":[],"timingStatus":"OTH","annotatedCoachRef":{}},"stopArea":["340G001856"],"adminArea":"096","plusbusZone":[],"created":"2003-09-08T00:00:00","updated":"2023-02-10T11:13:59","status":"active","validity":[]}}