{"370027307":{"atcoCode":"370027307","naptanCode":"37027307","category":"bus","stopType":"BCT","onStreet":true,"name":"Chapel Road/Hornbeam Close","landmark":"","street":"","crossing":"","locality":"Burncross","town":"Sheffield","suburb":"Burncross","coordinates":[-1.477769183,53.456059057],"indicator":"opp","properties":{"type":"marked","stopSubType":"MKD","bearing":"W","section":[],"timingStatus":"OTH","annotatedCoachRef":{}},"stopArea":["370G100139"],"adminArea":"099","plusbusZone":["SHEFFLD"],"created":"2008-09-05T12:00:00","updated":"2011-04-05T12:16:00","status":"active","validity":[]}}