{"40004406008B":{"atcoCode":"40004406008B","naptanCode":"surajgpm","category":"bus","stopType":"BCT","onStreet":true,"name":"Woodcote Side","landmark":"","street":"","crossing":"","locality":"Woodcote, Epsom","town":"Epsom","suburb":"Woodcote","coordinates":[-0.2780103,51.3193943],"indicator":"adj","properties":{"type":"custom","stopSubType":"CUS","bearing":"N","section":[],"timingStatus":"OTH","annotatedCoachRef":{}},"stopArea":["400G4406008A"],"adminArea":"102","plusbusZone":[],"created":"2004-12-01T00:00:00.000","updated":"2017-05-15T17:10:00.000","status":"active","validity":[]}}