{"410000010039":{"atcoCode":"410000010039","naptanCode":"twraptda","category":"bus","stopType":"BCT","onStreet":true,"name":"The Quadrant-Oswin Terrace","landmark":"","street":"","crossing":"","locality":"West Chirton","town":"North Tyneside","suburb":"West Chirton","coordinates":[-1.4674936,55.0088873],"indicator":"S-Bound","properties":{"type":"marked","stopSubType":"MKD","bearing":"S","section":[],"timingStatus":"OTH","annotatedCoachRef":{}},"stopArea":[],"adminArea":"103","plusbusZone":[],"created":"1998-12-31T15:25:28.000","updated":"2011-04-26T10:38:55.000","status":"active","validity":[]}}