{"450015609":{"atcoCode":"450015609","naptanCode":"45015609","category":"bus","stopType":"BCT","onStreet":true,"name":"Lee Green","landmark":"","street":"","crossing":"","locality":"Mirfield","town":"Northorpe","suburb":"","coordinates":[-1.688095288136488,53.68365679616656],"indicator":"opp","properties":{"type":"marked","stopSubType":"MKD","bearing":"SE","section":[],"timingStatus":"OTH","annotatedCoachRef":{}},"stopArea":["450G4950"],"adminArea":"107","plusbusZone":[],"created":"1999-01-05T00:00:00","updated":"2024-02-09T14:06:42","status":"active","validity":[{"validityStart":"1999-01-05","validityEnd":"","status":"","transferToStop":"","remarks":""}]}}