{"450025194":{"atcoCode":"450025194","naptanCode":"45025194","category":"bus","stopType":"BCT","onStreet":true,"name":"Helme Lane Broadlands Rd","landmark":"","street":"","crossing":"","locality":"Meltham","town":"Meltham","suburb":"","coordinates":[-1.852277933857988,53.59770268154714],"indicator":"at","properties":{"type":"marked","stopSubType":"MKD","bearing":"SW","section":[],"timingStatus":"OTH","annotatedCoachRef":{}},"stopArea":["450G1991"],"adminArea":"107","plusbusZone":[],"created":"2002-11-05T00:00:00","updated":"2020-12-07T11:16:50","status":"active","validity":[{"validityStart":"2002-11-05","validityEnd":"","status":"","transferToStop":"","remarks":""}]}}