{"490002061S":{"atcoCode":"490002061S","naptanCode":"54854","category":"bus","stopType":"BCT","onStreet":true,"name":"Mudchute","landmark":"","street":"","crossing":"","locality":"Mudchute","town":"","suburb":"","coordinates":[-0.01465,51.492],"indicator":"Stop MH","properties":{"type":"marked","stopSubType":"MKD","bearing":"S","section":[],"timingStatus":"OTH","annotatedCoachRef":{}},"stopArea":["490G02061B"],"adminArea":"082","plusbusZone":[],"created":"1970-01-01T00:00:00","updated":"2025-02-14T10:30:09","status":"active","validity":[]}}