{"490009076E":{"atcoCode":"490009076E","naptanCode":"77570","category":"bus","stopType":"BCT","onStreet":true,"name":"Leigham Court Road","landmark":"","street":"","crossing":"","locality":"Streatham Hill","town":"","suburb":"","coordinates":[-0.1272,51.43749],"indicator":"Stop E","properties":{"type":"marked","stopSubType":"MKD","bearing":"S","section":[],"timingStatus":"OTH","annotatedCoachRef":{}},"stopArea":["490G000632"],"adminArea":"082","plusbusZone":[],"created":"1970-01-01T00:00:00","updated":"2017-01-03T06:38:50","status":"active","validity":[]}}