{"490004862R":{"atcoCode":"490004862R","naptanCode":"77021","category":"bus","stopType":"BCT","onStreet":true,"name":"Catford & Catford Bridge Stns","landmark":"","street":"","crossing":"","locality":"Catford","town":"","suburb":"","coordinates":[-0.02411,51.44442],"indicator":"Stop R","properties":{"type":"marked","stopSubType":"MKD","bearing":"W","section":[],"timingStatus":"OTH","annotatedCoachRef":{}},"stopArea":["490G000444"],"adminArea":"082","plusbusZone":[],"created":"1970-01-01T00:00:00","updated":"2024-07-25T14:07:13","status":"active","validity":[]}}