{"5130AWD72265":{"atcoCode":"5130AWD72265","naptanCode":"cnwgapm","category":"bus","stopType":"BCT","onStreet":true,"name":"Bowling Green","landmark":"","street":"","crossing":"","locality":"Tywyn, Conwy","town":"","suburb":"","coordinates":[-3.824555553,53.293507444],"indicator":"o/s","properties":{"type":"marked","stopSubType":"MKD","bearing":"SE","section":[],"timingStatus":"OTH","annotatedCoachRef":{}},"stopArea":[],"adminArea":"014","plusbusZone":["LUDO"],"created":"2000-01-01T00:00:00","updated":"2024-04-26T16:10:08","status":"active","validity":[]}}