{"5140AWD71004":{"atcoCode":"5140AWD71004","naptanCode":"wregwam","category":"bus","stopType":"BCT","onStreet":true,"name":"Tan-y-Dre","landmark":"","street":"","crossing":"","locality":"Rhosnesni","town":"","suburb":"","coordinates":[-2.974931004,53.05077514],"indicator":"after","properties":{"type":"marked","stopSubType":"MKD","bearing":"NW","section":[],"timingStatus":"OTH","annotatedCoachRef":{}},"stopArea":[],"adminArea":"067","plusbusZone":["WREXHMG"],"created":"2000-01-01T00:00:00","updated":"2024-05-02T10:29:32","status":"active","validity":[]}}