{"5310WDB18079":{"atcoCode":"5310WDB18079","naptanCode":"nwpgwtj","category":"bus","stopType":"BCT","onStreet":true,"name":"Cold Bay Close","landmark":"","street":"","crossing":"","locality":"Rogerstone","town":"","suburb":"","coordinates":[-3.057994862,51.583865444],"indicator":"before","properties":{"type":"marked","stopSubType":"MKD","bearing":"W","section":[],"timingStatus":"OTH","annotatedCoachRef":{}},"stopArea":[],"adminArea":"035","plusbusZone":[],"created":"2022-08-04T12:24:11","updated":"2024-05-02T09:33:46","status":"active","validity":[{"validityStart":"2022-08-04","validityEnd":"","status":"","transferToStop":"","remarks":""}]}}