{"5410AWQ26221":{"atcoCode":"5410AWQ26221","naptanCode":"ynydjwj","category":"bus","stopType":"BCT","onStreet":true,"name":"Graig Las","landmark":"","street":"","crossing":"","locality":"Llangefni","town":"","suburb":"","coordinates":[-4.325397543,53.256504288],"indicator":"after","properties":{"type":"marked","stopSubType":"MKD","bearing":"SE","section":[],"timingStatus":"OTH","annotatedCoachRef":{}},"stopArea":[],"adminArea":"024","plusbusZone":[],"created":"2000-01-01T00:00:00","updated":"2025-07-31T09:11:40","status":"active","validity":[]}}