{"5520AWA14448":{"atcoCode":"5520AWA14448","naptanCode":"rhojdpd","category":"bus","stopType":"BCT","onStreet":true,"name":"Cilely Farm","landmark":"","street":"","crossing":"","locality":"Trebanog","town":"","suburb":"","coordinates":[-3.422107676,51.598212769],"indicator":"after","properties":{"type":"marked","stopSubType":"MKD","bearing":"NE","section":[],"timingStatus":"OTH","annotatedCoachRef":{}},"stopArea":[],"adminArea":"048","plusbusZone":[],"created":"2000-01-01T00:00:00","updated":"2024-05-02T09:43:51","status":"active","validity":[]}}