{"5540AWM21055":{"atcoCode":"5540AWM21055","naptanCode":"cpyatpw","category":"bus","stopType":"BCT","onStreet":true,"name":"Edwardsville","landmark":"","street":"","crossing":"","locality":"Cwmcarn","town":"","suburb":"","coordinates":[-3.130813745,51.637446836],"indicator":"in","properties":{"type":"marked","stopSubType":"MKD","bearing":"NW","section":[],"timingStatus":"OTH","annotatedCoachRef":{}},"stopArea":[],"adminArea":"010","plusbusZone":[],"created":"2000-01-01T00:00:00","updated":"2024-04-26T15:55:02","status":"active","validity":[]}}