{"5710AWA11654":{"atcoCode":"5710AWA11654","naptanCode":"cdiagmd","category":"bus","stopType":"BCT","onStreet":true,"name":"Britannia Quay","landmark":"","street":"","crossing":"","locality":"Cardiff Bay","town":"","suburb":"","coordinates":[-3.160838185,51.465104645],"indicator":"adj Alexander House","properties":{"type":"marked","stopSubType":"MKD","bearing":"SW","section":[],"timingStatus":"OTH","annotatedCoachRef":{}},"stopArea":[],"adminArea":"011","plusbusZone":["CRDFCEN"],"created":"2000-01-01T00:00:00","updated":"2025-09-11T13:31:54","status":"active","validity":[]}}