{"6020711009":{"atcoCode":"6020711009","naptanCode":"67525373","category":"bus","stopType":"BCT","onStreet":true,"name":"Mossedge Road End","landmark":"","street":"","crossing":"","locality":"South Ronaldsay","town":"","suburb":"","coordinates":[-2.93959,58.80469],"indicator":"at","properties":{"type":"custom","stopSubType":"CUS","bearing":"NE","section":[],"timingStatus":"OTH","annotatedCoachRef":{}},"stopArea":[],"adminArea":"134","plusbusZone":[],"created":"2015-09-21T00:00:00","updated":"2015-09-21T11:45:30","status":"active","validity":[]}}