{"6030145":{"atcoCode":"6030145","naptanCode":"45823969","category":"bus","stopType":"BCT","onStreet":true,"name":"Road End","landmark":"","street":"","crossing":"","locality":"Trondavoe","town":"","suburb":"","coordinates":[-1.31752,60.417246],"indicator":"opp","properties":{"type":"marked","stopSubType":"MKD","bearing":"SW","section":[],"timingStatus":"OTH","annotatedCoachRef":{}},"stopArea":["603G145"],"adminArea":"137","plusbusZone":[],"created":"2013-08-16T00:00:00.000","updated":"2023-07-25T14:16:57.001","status":"active","validity":[]}}