{"61501291":{"atcoCode":"61501291","naptanCode":"75234945","category":"bus","stopType":"BCT","onStreet":true,"name":"Dundonald","landmark":"","street":"","crossing":"","locality":"Thankerton","town":"THANKERTON","suburb":"","coordinates":[-3.630937497480495,55.62019648548435],"indicator":"At","properties":{"type":"custom","stopSubType":"CUS","bearing":"","section":[],"timingStatus":"OTH","annotatedCoachRef":{}},"stopArea":["615G14166"],"adminArea":"139","plusbusZone":[],"created":"2003-08-27T00:00:00","updated":"2023-12-12T15:02:54","status":"active","validity":[]}}