{"6290A15":{"atcoCode":"6290A15","naptanCode":"95623458","category":"bus","stopType":"BCT","onStreet":true,"name":"Cappers Court","landmark":"","street":"","crossing":"","locality":"Bathville","town":"","suburb":"","coordinates":[-3.700358,55.889612],"indicator":"opp","properties":{"type":"marked","stopSubType":"MKD","bearing":"N","section":[],"timingStatus":"OTH","annotatedCoachRef":{}},"stopArea":[],"adminArea":"141","plusbusZone":["BTHGATE"],"created":"2002-11-11T00:00:00.000","updated":"2023-09-25T12:33:41.778","status":"active","validity":[]}}