{"6500K0559":{"atcoCode":"6500K0559","naptanCode":"34327943","category":"bus","stopType":"BCT","onStreet":true,"name":"Sandwell Street","landmark":"","street":"","crossing":"","locality":"Buckhaven","town":"","suburb":"","coordinates":[-3.029753,56.174997],"indicator":"opp","properties":{"type":"marked","stopSubType":"MKD","bearing":"SW","section":[],"timingStatus":"OTH","annotatedCoachRef":{}},"stopArea":["650GK0558"],"adminArea":"126","plusbusZone":[],"created":"2002-11-26T00:00:00.000","updated":"2011-06-03T11:33:36.000","status":"active","validity":[]}}