{"6500N9886":{"atcoCode":"6500N9886","naptanCode":"34342649","category":"bus","stopType":"BCT","onStreet":true,"name":"Thornbank Cottage","landmark":"","street":"","crossing":"","locality":"Ceres","town":"","suburb":"","coordinates":[-2.97173,56.284363],"indicator":"Opp","properties":{"type":"custom","stopSubType":"CUS","bearing":"NW","section":[],"timingStatus":"OTH","annotatedCoachRef":{}},"stopArea":["650GN9752"],"adminArea":"126","plusbusZone":[],"created":"2003-11-06T00:00:00.000","updated":"2009-11-09T00:00:00.000","status":"inactive","validity":[{"validityStart":"2012-05-21","validityEnd":"","status":"","transferToStop":"","remarks":"No Services pass this stop"}]}}