{"66902380039":{"atcoCode":"66902380039","naptanCode":"32526296","category":"bus","stopType":"BCT","onStreet":true,"name":"Clydesdale Street","landmark":"","street":"","crossing":"","locality":"Boness","town":"","suburb":"","coordinates":[-3.606177,56.011714],"indicator":"after","properties":{"type":"marked","stopSubType":"MKD","bearing":"N","section":[],"timingStatus":"OTH","annotatedCoachRef":{}},"stopArea":["669G2380039"],"adminArea":"125","plusbusZone":["LNLTHGW"],"created":"2003-11-18T00:00:00.000","updated":"2003-11-18T00:00:00.000","status":"active","validity":[]}}