{"66903640018":{"atcoCode":"66903640018","naptanCode":"32525376","category":"bus","stopType":"BCT","onStreet":true,"name":"Balfour Crescent","landmark":"","street":"","crossing":"","locality":"Larbert","town":"","suburb":"","coordinates":[-3.829861,56.025797],"indicator":"opp","properties":{"type":"marked","stopSubType":"MKD","bearing":"N","section":[],"timingStatus":"OTH","annotatedCoachRef":{}},"stopArea":["669G3640018"],"adminArea":"125","plusbusZone":["FALKRKG"],"created":"1998-10-30T00:00:00.000","updated":"1998-10-30T00:00:00.000","status":"active","validity":[]}}