{"36a-aviemore-grantown":[{"filename":"_S_SC_SBLB_36A_1.json","mode":"bus","region":"S","lineId":["SBLB:PM0000005:753:36A"],"name":["36A"],"origin":"Aviemore","destination":"Grantown","vias":[],"description":"Aviemore - Grantown","operators":["SBLB"],"lastModified":"2025-05-28T11:46:09","publicUse":"false","startDate":"2025-05-28","endDate":"","routes":[{"routeId":"RT429","description":"Aviemore Opp Rail Stn - Grantown Burnfield Ave","stopPoints":["6700713303","6700600130","6700713509","6700600128","6700712394A","670085091","6700714102","6700237","6700235","6700233","6700731942","670091109A","670091108","6700713311A","670091105A","670091107","67009197"],"distance":[411,151,259,285,212,609,2598,997,1387,3946,11561,240,582,260,116,57],"direction":["","","","","","","","","","","","","","","",""]},{"routeId":"RT430","description":"Grantown Burnfield Ave - Aviemore Railway Stn","stopPoints":["67009197","670091106A","670091107A","670091105","670091108A","670091109","6700731942A","6700234","6700236","6700238","6700714103","670085091A","6700712394","6700600129","6700600129A","670084948","6700713317"],"distance":[737,335,159,745,246,11575,3983,1403,989,2595,650,181,304,242,208,357],"direction":["","","","","","","","","","","","","","","",""]}],"timetables":{"JP_36A-BB--SCHI-SBLB-ESIN-2025-05-28-IS_17th_SBLB_36A_1-3":[{"destinationDisplay":"Grantown Burnfield Ave","direction":"outbound","stopPoints":["6700713303","6700600130","6700713509","6700600128","6700712394A","670085091","6700714102","6700237","6700235","6700233","6700731942","670091109A","670091108","6700713311A","670091105A","670091107","67009197"],"runtimes":["PT1M0S","PT1M0S","PT0M0S","PT1M0S","PT0M0S","PT1M0S","PT3M0S","PT1M0S","PT1M0S","PT5M0S","PT12M0S","PT0M0S","PT1M0S","PT0M0S","PT1M0S","PT0M0S"],"activities":["pickUp","pickUpAndSetDown","pickUpAndSetDown","pickUpAndSetDown","pickUpAndSetDown","pickUpAndSetDown","pickUpAndSetDown","pickUpAndSetDown","pickUpAndSetDown","pickUpAndSetDown","pickUpAndSetDown","pickUpAndSetDown","pickUpAndSetDown","pickUpAndSetDown","pickUpAndSetDown","pickUpAndSetDown","setDown"],"waitTimes":["","","","","","","","","","","","","","","","",""],"timingStatuses":["PTP","otherPoint","PTP","otherPoint","otherPoint","otherPoint","otherPoint","otherPoint","otherPoint","otherPoint","PTP","otherPoint","otherPoint","otherPoint","PTP","otherPoint","PTP"],"lineId":"SBLB:PM0000005:753:36A","vehicle":"","schedules":[{"profiles":{"regular":["Monday","Tuesday","Wednesday","Thursday"],"special":{"notRunning":[{"startDate":"2023-05-08","endDate":"2023-05-08","note":""}]},"holidays":{"running":["LateSummerBankHolidayNotScotland","SpringBank","AugustBankHolidayScotland","ChristmasDayHoliday","BoxingDayHoliday","NewYearsDayHoliday","ChristmasEve","NewYearsEve"],"notRunning":["ChristmasDay","BoxingDay","GoodFriday","NewYearsDay","Jan2ndScotland","MayDay","EasterMonday"]},"servicedOrganisations":{"running":[{"WorkingDays":{"ServicedOrganisationRef":"Sch"}}]}},"departures":["11:25:00"],"dayShift":[0]},{"profiles":{"regular":["Monday","Tuesday","Wednesday","Thursday","Friday"],"special":{"notRunning":[{"startDate":"2024-12-23","endDate":"2025-01-05","note":""}]},"holidays":{"running":["LateSummerBankHolidayNotScotland","EasterMonday","SpringBank","AugustBankHolidayScotland","ChristmasDayHoliday","BoxingDayHoliday","NewYearsDayHoliday","ChristmasEve","NewYearsEve"],"notRunning":["ChristmasDay","BoxingDay","GoodFriday","NewYearsDay","Jan2ndScotland","MayDay"]}},"departures":["09:25:00","16:35:00"],"dayShift":[0,0]},{"profiles":{"regular":["Monday","Tuesday","Wednesday","Thursday","Friday"],"special":{"notRunning":[{"startDate":"2023-05-08","endDate":"2023-05-08","note":""}]},"holidays":{"running":["EasterMonday","SpringBank","AugustBankHolidayScotland","ChristmasDayHoliday","BoxingDayHoliday","NewYearsDayHoliday","ChristmasEve","NewYearsEve"],"notRunning":["ChristmasDay","BoxingDay","GoodFriday","NewYearsDay","Jan2ndScotland","LateSummerBankHolidayNotScotland","MayDay"]},"servicedOrganisations":{"running":[{"Holidays":{"ServicedOrganisationRef":"Sch"}}]}},"departures":["12:25:00"],"dayShift":[0]},{"profiles":{"regular":["Friday"],"holidays":{"running":["ChristmasDayHoliday","BoxingDayHoliday","NewYearsDayHoliday","ChristmasEve","NewYearsEve"],"notRunning":["ChristmasDay","BoxingDay","GoodFriday","NewYearsDay","Jan2ndScotland","LateSummerBankHolidayNotScotland","MayDay","EasterMonday","SpringBank","AugustBankHolidayScotland"]},"servicedOrganisations":{"running":[{"WorkingDays":{"ServicedOrganisationRef":"Sch"}}]}},"departures":["14:25:00"],"dayShift":[0]}]}],"JP_36A-BB--SCHI-SBLB-ESIN-2025-05-28-IS_17th_SBLB_36A_1-4":[{"destinationDisplay":"Aviemore Railway Stn","direction":"inbound","stopPoints":["67009197","670091106A","670091107A","670091105","670091108A","670091109","6700731942A","6700234","6700236","6700238","6700714103","670085091A","6700712394","6700600129","6700600129A","670084948","6700713317"],"runtimes":["PT1M0S","PT1M0S","PT0M0S","PT1M0S","PT0M0S","PT12M0S","PT5M0S","PT1M0S","PT1M0S","PT3M0S","PT1M0S","PT0M0S","PT1M0S","PT0M0S","PT1M0S","PT1M0S"],"activities":["pickUp","pickUpAndSetDown","pickUpAndSetDown","pickUpAndSetDown","pickUpAndSetDown","pickUpAndSetDown","pickUpAndSetDown","pickUpAndSetDown","pickUpAndSetDown","pickUpAndSetDown","pickUpAndSetDown","pickUpAndSetDown","pickUpAndSetDown","pickUpAndSetDown","pickUpAndSetDown","pickUpAndSetDown","setDown"],"waitTimes":["","","","","","","","","","","","","","","","",""],"timingStatuses":["PTP","otherPoint","otherPoint","PTP","otherPoint","otherPoint","PTP","otherPoint","otherPoint","otherPoint","otherPoint","otherPoint","otherPoint","otherPoint","PTP","otherPoint","PTP"],"lineId":"SBLB:PM0000005:753:36A","vehicle":"","schedules":[{"profiles":{"regular":["Monday","Tuesday","Wednesday","Thursday"],"special":{"notRunning":[{"startDate":"2023-05-08","endDate":"2023-05-08","note":""}]},"holidays":{"running":["LateSummerBankHolidayNotScotland","SpringBank","AugustBankHolidayScotland","ChristmasDayHoliday","BoxingDayHoliday","NewYearsDayHoliday","ChristmasEve","NewYearsEve"],"notRunning":["ChristmasDay","BoxingDay","GoodFriday","NewYearsDay","Jan2ndScotland","MayDay","EasterMonday"]},"servicedOrganisations":{"running":[{"WorkingDays":{"ServicedOrganisationRef":"Sch"}}]}},"departures":["13:41:00"],"dayShift":[0]},{"profiles":{"regular":["Monday","Tuesday","Wednesday","Thursday","Friday"],"special":{"notRunning":[{"startDate":"2024-12-23","endDate":"2025-01-05","note":""}]},"holidays":{"running":["LateSummerBankHolidayNotScotland","EasterMonday","SpringBank","AugustBankHolidayScotland","ChristmasDayHoliday","BoxingDayHoliday","NewYearsDayHoliday","ChristmasEve","NewYearsEve"],"notRunning":["ChristmasDay","BoxingDay","GoodFriday","NewYearsDay","Jan2ndScotland","MayDay"]}},"departures":["11:41:00","18:48:00"],"dayShift":[0,0]},{"profiles":{"regular":["Monday","Tuesday","Wednesday","Thursday","Friday"],"special":{"notRunning":[{"startDate":"2023-05-08","endDate":"2023-05-08","note":""}]},"holidays":{"running":["EasterMonday","SpringBank","AugustBankHolidayScotland","ChristmasDayHoliday","BoxingDayHoliday","NewYearsDayHoliday","ChristmasEve","NewYearsEve"],"notRunning":["ChristmasDay","BoxingDay","GoodFriday","NewYearsDay","Jan2ndScotland","LateSummerBankHolidayNotScotland","MayDay"]},"servicedOrganisations":{"running":[{"Holidays":{"ServicedOrganisationRef":"Sch"}}]}},"departures":["14:41:00"],"dayShift":[0]},{"profiles":{"regular":["Friday"],"holidays":{"running":["ChristmasDayHoliday","BoxingDayHoliday","NewYearsDayHoliday","ChristmasEve","NewYearsEve"],"notRunning":["ChristmasDay","BoxingDay","GoodFriday","NewYearsDay","Jan2ndScotland","LateSummerBankHolidayNotScotland","MayDay","EasterMonday","SpringBank","AugustBankHolidayScotland"]},"servicedOrganisations":{"running":[{"WorkingDays":{"ServicedOrganisationRef":"Sch"}}]}},"departures":["16:41:00"],"dayShift":[0]}]}]},"vehicles":{"":{"description":""}},"servicedOrganisations":{"Sch":{"name":"Schooldays only","workingDays":[{"startDate":"2025-01-06","endDate":"2025-02-14","description":"Schooldays only"},{"startDate":"2025-02-20","endDate":"2025-04-04","description":"Schooldays only"},{"startDate":"2025-04-22","endDate":"2025-05-02","description":"Schooldays only"},{"startDate":"2025-05-06","endDate":"2025-05-30","description":"Schooldays only"},{"startDate":"2025-06-03","endDate":"2025-07-03","description":"Schooldays only"},{"startDate":"2025-08-19","endDate":"2025-09-12","description":"Schooldays only"},{"startDate":"2025-09-17","endDate":"2025-10-10","description":"Schooldays only"},{"startDate":"2025-11-24","endDate":"2025-12-23","description":"Schooldays only"},{"startDate":"2026-01-08","endDate":"2026-02-13","description":"Schooldays only"}]}}}]}